readmeai/__init__.py
readmeai/assets/badges/shieldsio.json
readmeai/assets/badges/skillicons.json
readmeai/assets/logos/animated.svg
readmeai/assets/logos/aurora.svg
readmeai/assets/logos/blue.svg
readmeai/assets/logos/green.svg
readmeai/assets/logos/ice.svg
readmeai/assets/logos/metallic.svg
readmeai/assets/logos/midnight.svg
readmeai/assets/logos/orange.svg
readmeai/assets/logos/purple.svg
readmeai/assets/logos/rainbow.svg
readmeai/assets/logos/terminal.svg
readmeai/cli/__init__.py
readmeai/cli/main.py
readmeai/cli/options.py
readmeai/config/__init__.py
readmeai/config/settings/badge-list.toml
readmeai/config/settings/commands.toml
readmeai/config/settings/config.toml
readmeai/config/settings/dev-setup.toml
readmeai/config/settings/dev-tools.toml
readmeai/config/settings/ignore-list.toml
readmeai/config/settings/language-map.toml
readmeai/config/settings/project-manifest.toml
readmeai/config/settings/prompts.toml
readmeai/config/settings/templates/banners.toml
readmeai/config/settings/templates/headers.toml
readmeai/config/settings/templates/quickstart.toml
readmeai/config/settings/templates.toml
readmeai/config/settings/themes/emojis.yaml
readmeai/config/settings.py
readmeai/core/__init__.py
readmeai/core/errors.py
readmeai/core/logger.py
readmeai/core/pipeline.py
readmeai/extractors/__init__.py
readmeai/extractors/analyzer.py
readmeai/extractors/dependencies.py
readmeai/extractors/metadata.py
readmeai/extractors/models.py
readmeai/extractors/tools.py
readmeai/generators/__init__.py
readmeai/generators/badges.py
readmeai/generators/banners/__init__.py
readmeai/generators/banners/ascii.py
readmeai/generators/banners/svg.py
readmeai/generators/builder.py
readmeai/generators/colors/__init__.py
readmeai/generators/colors/converters.py
readmeai/generators/colors/gradients.py
readmeai/generators/emojis.py
readmeai/generators/enums.py
readmeai/generators/headers.py
readmeai/generators/navigation.py
readmeai/generators/quickstart.py
readmeai/generators/tables.py
readmeai-0.6.3.dist-info/LICENSE
readmeai-0.6.3.dist-info/METADATA
readmeai-0.6.3.dist-info/WHEEL
readmeai-0.6.3.dist-info/entry_points.txt
readmeai-0.6.3.dist-info/RECORD
