Metadata-Version: 2.3
Name: readmeai
Version: 0.6.3
Summary: Automated README file generator, powered by AI.
License: MIT
Keywords: ai-documentation,ai-powered,ai-readme,automatic-documentation,chat-gpt,cli,code-documentation,developer-tools,documentation-automation,gemini,github-documentation,gpt-4,llm,markdown-generator,openai,project-documentation,readme-ai,readme-automation,readme-generator,software-documentation
Author: Eli Salamie
Author-email: egsalamie@gmail.com
Requires-Python: >=3.9,<4.0
Classifier: Development Status :: 4 - Beta
Classifier: Environment :: Console
Classifier: Framework :: Pydantic
Classifier: Framework :: Pytest
Classifier: Intended Audience :: Developers
Classifier: Intended Audience :: Information Technology
Classifier: Intended Audience :: Science/Research
Classifier: License :: OSI Approved :: MIT License
Classifier: Natural Language :: English
Classifier: Operating System :: MacOS
Classifier: Operating System :: Microsoft :: Windows
Classifier: Programming Language :: Python
Classifier: Programming Language :: Python :: 3
Classifier: Programming Language :: Python :: 3.9
Classifier: Programming Language :: Python :: 3.10
Classifier: Programming Language :: Python :: 3.11
Classifier: Programming Language :: Python :: 3.12
Classifier: Programming Language :: Python :: 3.13
Classifier: Programming Language :: Python :: 3 :: Only
Classifier: Topic :: Documentation
Classifier: Topic :: Scientific/Engineering :: Artificial Intelligence
Classifier: Topic :: Software Development
Classifier: Topic :: Software Development :: Documentation
Classifier: Topic :: Text Processing :: Markup :: Markdown
Provides-Extra: anthropic
Provides-Extra: google-generativeai
Requires-Dist: aiohttp (>=3.9.5,<4.0.0)
Requires-Dist: anthropic ; extra == "anthropic"
Requires-Dist: click (>=8.1.7,<9.0.0)
Requires-Dist: gitpython (>=3.1.31,<4.0.0)
Requires-Dist: google-generativeai ; extra == "google-generativeai"
Requires-Dist: openai
Requires-Dist: pydantic
Requires-Dist: pydantic-extra-types
Requires-Dist: pydantic-settings
Requires-Dist: pyyaml (>=6.0.1,<7.0.0)
Requires-Dist: structlog (>=24.4.0,<25.0.0)
Requires-Dist: tenacity (>=8.2.2,<9.0.0)
Requires-Dist: tiktoken (>=0.4.0,<0.5.0)
Requires-Dist: tomli ; python_version < "3.11"
Requires-Dist: typing-extensions ; python_version < "3.11"
Project-URL: Documentation, https://eli64s.github.io/readme-ai
Project-URL: Homepage, https://github.com/eli64s/readme-ai
